fastapi_allowed_hosts/__init__.py
fastapi_allowed_hosts/allowed_host_middleware.py
fastapi_allowed_hosts/exceptions.py
fastapi_allowed_hosts-0.1.0.dist-info/LICENSE
fastapi_allowed_hosts-0.1.0.dist-info/METADATA
fastapi_allowed_hosts-0.1.0.dist-info/WHEEL
fastapi_allowed_hosts-0.1.0.dist-info/RECORD
