Metadata-Version: 2.3
Name: fastapi-allowed-hosts
Version: 0.1.0
Summary: A FastAPI middleware for validating Host headers against allowed hosts, inspired by Django's ALLOWED_HOSTS
License: MIT
Keywords: fastapi,middleware,security,allowed-hosts,host-validation,starlette
Author: Georgios Semerdzhiev
Author-email: asenov01@hotmail.com
Requires-Python: >=3.14
Classifier: Development Status :: 4 - Beta
Classifier: Environment :: Web Environment
Classifier: Framework :: FastAPI
Classifier: Intended Audience :: Developers
Classifier: License :: OSI Approved :: MIT License
Classifier: Operating System :: OS Independent
Classifier: Programming Language :: Python :: 3
Classifier: Programming Language :: Python :: 3.14
Classifier: Topic :: Internet :: WWW/HTTP :: HTTP Servers
Classifier: Topic :: Security
Classifier: Typing :: Typed
Provides-Extra: dev
Requires-Dist: fastapi (>=0.128.0,<0.129.0)
Requires-Dist: httpx (>=0.28.0,<0.29.0) ; extra == "dev"
Requires-Dist: pytest (>=9.0.2,<10.0.0) ; extra == "dev"
Requires-Dist: ruff (>=0.14.10,<0.15.0) ; extra == "dev"
Project-URL: Documentation, https://github.com/georgios48/fastapi-allowed-hosts
Project-URL: Homepage, https://github.com/georgios48/fastapi-allowed-hosts
Project-URL: Repository, https://github.com/georgios48/fastapi-allowed-hosts
